txjsonrpc_ng/__init__.py
txjsonrpc_ng/auth.py
txjsonrpc_ng/jsonrpc.py
txjsonrpc_ng/jsonrpclib.py
txjsonrpc_ng/meta.py
txjsonrpc_ng/netstring/__init__.py
txjsonrpc_ng/netstring/jsonrpc.py
txjsonrpc_ng/scripts/__init__.py
txjsonrpc_ng/scripts/getVersion.py
txjsonrpc_ng/testing/__init__.py
txjsonrpc_ng/testing/suite.py
txjsonrpc_ng/util/__init__.py
txjsonrpc_ng/util/dist.py
txjsonrpc_ng/versions/__init__.py
txjsonrpc_ng/versions/versions.py
txjsonrpc_ng/web/__init__.py
txjsonrpc_ng/web/data.py
txjsonrpc_ng/web/jsonrpc.py
txjsonrpc_ng/web/render.py
txjsonrpc_ng-0.7.3.dist-info/LICENSE
txjsonrpc_ng-0.7.3.dist-info/METADATA
txjsonrpc_ng-0.7.3.dist-info/WHEEL
txjsonrpc_ng-0.7.3.dist-info/RECORD
