Metadata-Version: 2.3
Name: txjsonrpc-ng
Version: 0.7.3
Summary: Code for creatig Twisted JSON-RPC servers and clients.
License: BSD, GPL
Author: Duncan McGreggor
Author-email: oubiwann@adytum.us>, Andreas Wuerl <andi@tryb.de
Requires-Python: >=3.9,<4.0
Classifier: License :: Other/Proprietary License
Classifier: Programming Language :: Python :: 3
Classifier: Programming Language :: Python :: 3.9
Classifier: Programming Language :: Python :: 3.10
Classifier: Programming Language :: Python :: 3.11
Classifier: Programming Language :: Python :: 3.12
Classifier: Programming Language :: Python :: 3.13
Requires-Dist: Twisted (>=23.10,<24.0)
